[
    {
      "id": 10,
      "title": "Ultimate Facts - Did You Know? - Apps on Google Play",
      "url": "https://play.google.com/store/apps/details?id=com.viyatek.ultimatefacts",
      "notes": "Daily Interesting, Informative and Weird Random Facts! “Habits are powerful factors in our lives. Because they are consistent, often unconscious patterns, they constantly, daily, express our character and produce our effectiveness",
      "collectionId": 101,
      "createdAt": "27 May 2020",
      "updatedAt": "2020-08-22T04:06:40.604Z",
      "isFav": true,
      "iconUrl": "https://css-tricks.com/favicon.ico",
      "tags": {
        "id": 0,
        "name": "tag 1"
      }
    },
    {
        "id": 20,
        "title": "15 of the Best Web Design Books Every Designer and Developer Should Read | Elementor",
        "url": "https://csstricks.com",
        "notes": "From guides about UX design to books about coding — explore these 15 books and learn more about the many different aspects of web design.",
        "collectionId": 101,
        "createdAt": "12 June 2020",
        "updatedAt": "2020-08-22T04:06:40.604Z",
        "isFav": true,
        "iconUrl": "https://up.raindrop.io/collection/thumbs/126/150/04/f3d245b609f5a1268422eb515b6f8913.png",
        "tags": {
          "id": 0,
          "name": "tag 1"
        }
      },
      {
        "id": 30,
        "title": "Life Hack Tips - Daily Tips for your Life - Apps on Google Play",
        "url": "https://play.google.com/store/apps/details?id=com.fireshooters.lifetips",
        "notes": "This life tips app is a free and easy-to-use application contains tons of life tips in different categories such as technology tricks, health and drinks, money savers, etc. With these life tips you",
        "collectionId": 101,
        "createdAt": "12 Nov 2020",
        "updatedAt": "2020-08-22T04:06:40.604Z",
        "isFav": true,
        "iconUrl": "https://up.raindrop.io/collection/thumbs/126/150/04/f3d245b609f5a1268422eb515b6f8913.png",
        "tags": {
          "id": 0,
          "name": "tag 1"
        }
      }
      
  ]